neurological_lrd_analysis/__init__.py
neurological_lrd_analysis/biomedical_hurst_factory.py
neurological_lrd_analysis/benchmark_backends/__init__.py
neurological_lrd_analysis/benchmark_backends/selector.py
neurological_lrd_analysis/benchmark_core/__init__.py
neurological_lrd_analysis/benchmark_core/biomedical_scenarios.py
neurological_lrd_analysis/benchmark_core/generation.py
neurological_lrd_analysis/benchmark_core/runner.py
neurological_lrd_analysis/benchmark_core/visualization.py
neurological_lrd_analysis/benchmark_registry/__init__.py
neurological_lrd_analysis/benchmark_registry/registry.py
neurological_lrd_analysis-0.4.1.dist-info/licenses/LICENSE
neurological_lrd_analysis-0.4.1.dist-info/METADATA
neurological_lrd_analysis-0.4.1.dist-info/WHEEL
neurological_lrd_analysis-0.4.1.dist-info/top_level.txt
neurological_lrd_analysis-0.4.1.dist-info/RECORD
