Metadata-Version: 2.4
Name: neurological-lrd-analysis
Version: 0.4.1
Summary: Physics-Informed Fractional Operator Learning for Real-Time Neurological Biomarker Detection: A Framework for Memory-Driven EEG Analysis
Home-page: https://github.com/dave2k77/neurological_lrd_analysis
Author: Davian R. Chin
Author-email: "Davian R. Chin" <d.r.chin@pgr.reading.ac.uk>
Maintainer-email: "Davian R. Chin" <d.r.chin@pgr.reading.ac.uk>
License: MIT
Project-URL: Homepage, https://github.com/dave2k77/neurological_lrd_analysis
Project-URL: Documentation, https://neurological-lrd-analysis.readthedocs.io
Project-URL: Repository, https://github.com/dave2k77/neurological_lrd_analysis.git
Project-URL: Issues, https://github.com/dave2k77/neurological_lrd_analysis/issues
Project-URL: Author ORCiD, https://orcid.org/0009-0003-9434-3919
Project-URL: Changelog, https://github.com/dave2k77/neurological_lrd_analysis/blob/main/CHANGELOG.md
Keywords: hurst,long-range-dependence,neurological,time-series,fractal,eeg,ecg,neuroscience,wavelet,multifractal,benchmarking,biomedical,physics-informed,fractional-operators,machine-learning,biomarker-detection,memory-driven,real-time,fractional-calculus
Classifier: Development Status :: 4 - Beta
Classifier: Intended Audience :: Science/Research
Classifier: Intended Audience :: Healthcare Industry
Classifier: License :: OSI Approved :: MIT License
Classifier: Operating System :: OS Independent
Classifier: Programming Language :: Python :: 3
Classifier: Programming Language :: Python :: 3.11
Classifier: Programming Language :: Python :: 3.12
Classifier: Topic :: Scientific/Engineering :: Mathematics
Classifier: Topic :: Scientific/Engineering :: Medical Science Apps.
Classifier: Topic :: Scientific/Engineering :: Bio-Informatics
Classifier: Topic :: Scientific/Engineering :: Information Analysis
Classifier: Environment :: GPU
Classifier: Environment :: Console
Requires-Python: >=3.11
License-File: LICENSE
Requires-Dist: numpy>=1.24.0
Requires-Dist: scipy>=1.10.0
Requires-Dist: pandas>=2.0.0
Requires-Dist: scikit-learn>=1.3.0
Requires-Dist: matplotlib>=3.7.0
Requires-Dist: seaborn>=0.12.0
Requires-Dist: numba>=0.57.0
Requires-Dist: jax>=0.4.1
Requires-Dist: jaxlib>=0.4.1
Requires-Dist: flax>=0.7.0
Requires-Dist: optax>=0.1.0
Requires-Dist: numpyro>=0.13.0
Requires-Dist: hpfracc>=0.1.0
Requires-Dist: pywt>=1.4.0
Requires-Dist: fbm>=0.1.0
Provides-Extra: dev
Requires-Dist: pytest>=7.0.0; extra == "dev"
Requires-Dist: pytest-cov>=4.0.0; extra == "dev"
Requires-Dist: pytest-html>=3.0.0; extra == "dev"
Requires-Dist: pytest-json-report>=1.5.0; extra == "dev"
Requires-Dist: pytest-timeout>=2.1.0; extra == "dev"
Requires-Dist: psutil>=5.9.0; extra == "dev"
Requires-Dist: black>=23.0.0; extra == "dev"
Requires-Dist: isort>=5.12.0; extra == "dev"
Requires-Dist: flake8>=6.0.0; extra == "dev"
Requires-Dist: mypy>=1.0.0; extra == "dev"
Provides-Extra: docs
Requires-Dist: sphinx>=6.0.0; extra == "docs"
Requires-Dist: sphinx-rtd-theme>=1.2.0; extra == "docs"
Requires-Dist: myst-parser>=1.0.0; extra == "docs"
Provides-Extra: gpu
Requires-Dist: jax[cuda12_pip]>=0.4.1; extra == "gpu"
Requires-Dist: cupy-cuda12x>=12.0.0; extra == "gpu"
Dynamic: author
Dynamic: home-page
Dynamic: license-file
Dynamic: requires-python
